yum_hal/__init__.py
yum_hal/echo_worker.py
yum_hal/errors.py
yum_hal/manager.py
yum_hal/ticket.py
yum_hal/worker.py
yum_hal-0.1.3.dist-info/METADATA
yum_hal-0.1.3.dist-info/WHEEL
yum_hal-0.1.3.dist-info/top_level.txt
yum_hal-0.1.3.dist-info/RECORD
