Metadata-Version: 2.1
Name: yum-hal
Version: 0.1.3
Summary: yummy hardware access layer
Author-email: 袁首京 <yuanshoujing@gmail.com>
License: Apache-2.0
Keywords: hardware
Classifier: Programming Language :: Python :: 3
Requires-Python: >=3.7
Requires-Dist: msgpack
Requires-Dist: loguru
Provides-Extra: dev
Requires-Dist: build ; extra == 'dev'
Requires-Dist: twine ; extra == 'dev'
Requires-Dist: black ; extra == 'dev'
Provides-Extra: test
Requires-Dist: pytest ; extra == 'test'
